{
	"credit": "Made with Blockbench",
	"render_type": "cutout_mipped", "textures": {
		"0": "maidensmerrymaking:block/garland_horizontal",
		"1": "maidensmerrymaking:block/garland_bow",
		"particle": "maidensmerrymaking:block/garland_horizontal"
	},
	"elements": [
		{
			"from": [9, -2.9, 1.9],
			"to": [17, 13.1, 1.9],
			"shade": false,
			"rotation": {"angle": 0, "axis": "y", "origin": [2, 5, 3]},
			"faces": {
				"north": {"uv": [0, 0, 16, 8], "rotation": 90, "texture": "#0"},
				"east": {"uv": [0, 0, 16, 0], "rotation": 270, "texture": "#0"},
				"south": {"uv": [0, 0, 16, 8], "rotation": 270, "texture": "#0"},
				"west": {"uv": [0, 0, 16, 0], "rotation": 270, "texture": "#0"},
				"up": {"uv": [0, 0, 0, 8], "rotation": 270, "texture": "#0"},
				"down": {"uv": [0, 0, 0, 8], "rotation": 270, "texture": "#0"}
			}
		},
		{
			"from": [9, -2.9, 4],
			"to": [17, 13.1, 4],
			"shade": false,
			"rotation": {"angle": 0, "axis": "y", "origin": [2, 5, 3]},
			"faces": {
				"north": {"uv": [0, 0, 16, 8], "rotation": 90, "texture": "#0"},
				"east": {"uv": [0, 0, 16, 0], "rotation": 270, "texture": "#0"},
				"south": {"uv": [0, 0, 16, 8], "rotation": 270, "texture": "#0"},
				"west": {"uv": [0, 0, 16, 0], "rotation": 270, "texture": "#0"},
				"up": {"uv": [0, 0, 0, 8], "rotation": 270, "texture": "#0"},
				"down": {"uv": [0, 0, 0, 8], "rotation": 270, "texture": "#0"}
			}
		},
		{
			"from": [9.1, 0.3, -0.1],
			"to": [17.1, 0.3, 5.9],
			"shade": false,
			"rotation": {"angle": 0, "axis": "y", "origin": [2, 5, 3]},
			"faces": {
				"north": {"uv": [0, 0, 0, 8], "rotation": 90, "texture": "#0"},
				"east": {"uv": [0, 0, 0, 6], "rotation": 270, "texture": "#0"},
				"south": {"uv": [0, 0, 0, 8], "rotation": 270, "texture": "#0"},
				"west": {"uv": [0, 0, 0, 6], "rotation": 270, "texture": "#0"},
				"up": {"uv": [0, 0, 6, 8], "rotation": 270, "texture": "#0"},
				"down": {"uv": [0, 0, 6, 8], "rotation": 270, "texture": "#0"}
			}
		},
		{
			"from": [9, 9.9, -0.1],
			"to": [17, 9.9, 5.9],
			"shade": false,
			"rotation": {"angle": 0, "axis": "y", "origin": [2, 5, 3]},
			"faces": {
				"north": {"uv": [0, 0, 0, 8], "rotation": 90, "texture": "#0"},
				"east": {"uv": [0, 0, 0, 6], "rotation": 270, "texture": "#0"},
				"south": {"uv": [0, 0, 0, 8], "rotation": 270, "texture": "#0"},
				"west": {"uv": [0, 0, 0, 6], "rotation": 270, "texture": "#0"},
				"up": {"uv": [0, 0, 6, 8], "rotation": 270, "texture": "#0"},
				"down": {"uv": [0, 0, 6, 8], "rotation": 270, "texture": "#0"}
			}
		},
		{
			"name": "bow top",
			"from": [13.5, 10, 4.25],
			"to": [18.5, 16, 4.25],
			"rotation": {"angle": 0, "axis": "y", "origin": [2, 5, 3]},
			"faces": {
				"north": {"uv": [5, 5, 10, 11], "texture": "#1"},
				"east": {"uv": [0, 0, 0, 6], "texture": "#1"},
				"south": {"uv": [5, 5, 10, 11], "texture": "#1"},
				"west": {"uv": [0, 0, 0, 6], "texture": "#1"},
				"up": {"uv": [0, 0, 5, 0], "texture": "#1"},
				"down": {"uv": [0, 0, 5, 0], "texture": "#1"}
			}
		},
		{
			"name": "bow top",
			"from": [13.5, 10, 1.85],
			"to": [18.5, 16, 1.85],
			"rotation": {"angle": 0, "axis": "y", "origin": [2, 5, 3]},
			"faces": {
				"north": {"uv": [5, 5, 10, 11], "texture": "#1"},
				"east": {"uv": [0, 0, 0, 6], "texture": "#1"},
				"south": {"uv": [5, 5, 10, 11], "texture": "#1"},
				"west": {"uv": [0, 0, 0, 6], "texture": "#1"},
				"up": {"uv": [0, 0, 5, 0], "texture": "#1"},
				"down": {"uv": [0, 0, 5, 0], "texture": "#1"}
			}
		},
		{
			"name": "bow top",
			"from": [13.5, -6, 4.05],
			"to": [18.5, 0, 4.05],
			"rotation": {"angle": 0, "axis": "y", "origin": [2, 5, 3]},
			"faces": {
				"north": {"uv": [5, 5, 10, 11], "texture": "#1"},
				"east": {"uv": [0, 0, 0, 6], "texture": "#1"},
				"south": {"uv": [5, 5, 10, 11], "texture": "#1"},
				"west": {"uv": [0, 0, 0, 6], "texture": "#1"},
				"up": {"uv": [0, 0, 5, 0], "texture": "#1"},
				"down": {"uv": [0, 0, 5, 0], "texture": "#1"}
			}
		},
		{
			"name": "bow top",
			"from": [13.5, -6, 1.65],
			"to": [18.5, 0, 1.65],
			"rotation": {"angle": 0, "axis": "y", "origin": [2, 5, 3]},
			"faces": {
				"north": {"uv": [5, 5, 10, 11], "texture": "#1"},
				"east": {"uv": [0, 0, 0, 6], "texture": "#1"},
				"south": {"uv": [5, 5, 10, 11], "texture": "#1"},
				"west": {"uv": [0, 0, 0, 6], "texture": "#1"},
				"up": {"uv": [0, 0, 5, 0], "texture": "#1"},
				"down": {"uv": [0, 0, 5, 0], "texture": "#1"}
			}
		},
		{
			"from": [0.1, 8, 1.9],
			"to": [16.1, 16, 1.9],
			"rotation": {"angle": 0, "axis": "y", "origin": [13, 16, 2]},
			"faces": {
				"north": {"uv": [0, 0, 16, 8], "texture": "#0"},
				"east": {"uv": [0, 0, 0, 8], "texture": "#0"},
				"south": {"uv": [0, 0, 16, 8], "texture": "#0"},
				"west": {"uv": [0, 0, 0, 8], "texture": "#0"},
				"up": {"uv": [0, 0, 16, 0], "texture": "#0"},
				"down": {"uv": [0, 0, 16, 0], "texture": "#0"}
			}
		},
		{
			"from": [0.1, 8, 3.9],
			"to": [16.1, 16, 3.9],
			"rotation": {"angle": 0, "axis": "y", "origin": [13, 16, 2]},
			"faces": {
				"north": {"uv": [0, 0, 16, 8], "texture": "#0"},
				"east": {"uv": [0, 0, 0, 8], "texture": "#0"},
				"south": {"uv": [0, 0, 16, 8], "texture": "#0"},
				"west": {"uv": [0, 0, 0, 8], "texture": "#0"},
				"up": {"uv": [0, 0, 16, 0], "texture": "#0"},
				"down": {"uv": [0, 0, 16, 0], "texture": "#0"}
			}
		},
		{
			"from": [2.6, 7.9, -0.1],
			"to": [2.6, 15.9, 5.9],
			"rotation": {"angle": 0, "axis": "y", "origin": [13, 16, 2]},
			"faces": {
				"north": {"uv": [0, 0, 0, 8], "texture": "#0"},
				"east": {"uv": [0, 0, 6, 8], "texture": "#0"},
				"south": {"uv": [0, 0, 0, 8], "texture": "#0"},
				"west": {"uv": [0, 0, 6, 8], "texture": "#0"},
				"up": {"uv": [0, 0, 0, 6], "texture": "#0"},
				"down": {"uv": [0, 0, 0, 6], "texture": "#0"}
			}
		},
		{
			"from": [13.5, 8, -0.1],
			"to": [13.5, 16, 5.9],
			"rotation": {"angle": 0, "axis": "y", "origin": [13, 16, 2]},
			"faces": {
				"north": {"uv": [0, 0, 0, 8], "texture": "#0"},
				"east": {"uv": [0, 0, 6, 8], "texture": "#0"},
				"south": {"uv": [0, 0, 0, 8], "texture": "#0"},
				"west": {"uv": [0, 0, 6, 8], "texture": "#0"},
				"up": {"uv": [0, 0, 0, 6], "texture": "#0"},
				"down": {"uv": [0, 0, 0, 6], "texture": "#0"}
			}
		},
		{
			"name": "bow top",
			"from": [13.55, 10, 4.25],
			"to": [18.55, 16, 4.25],
			"rotation": {"angle": 0, "axis": "y", "origin": [13, 16, 2]},
			"faces": {
				"north": {"uv": [5, 5, 10, 11], "texture": "#1"},
				"east": {"uv": [0, 0, 0, 6], "texture": "#1"},
				"south": {"uv": [5, 5, 10, 11], "texture": "#1"},
				"west": {"uv": [0, 0, 0, 6], "texture": "#1"},
				"up": {"uv": [0, 0, 5, 0], "texture": "#1"},
				"down": {"uv": [0, 0, 5, 0], "texture": "#1"}
			}
		},
		{
			"name": "bow top",
			"from": [13.55, 10, 1.85],
			"to": [18.55, 16, 1.85],
			"rotation": {"angle": 0, "axis": "y", "origin": [13, 16, 2]},
			"faces": {
				"north": {"uv": [5, 5, 10, 11], "texture": "#1"},
				"east": {"uv": [0, 0, 0, 6], "texture": "#1"},
				"south": {"uv": [5, 5, 10, 11], "texture": "#1"},
				"west": {"uv": [0, 0, 0, 6], "texture": "#1"},
				"up": {"uv": [0, 0, 5, 0], "texture": "#1"},
				"down": {"uv": [0, 0, 5, 0], "texture": "#1"}
			}
		},
		{
			"name": "bow top",
			"from": [-2.45, 10, 4.05],
			"to": [2.55, 16, 4.05],
			"rotation": {"angle": 0, "axis": "y", "origin": [13, 16, 2]},
			"faces": {
				"north": {"uv": [5, 5, 10, 11], "texture": "#1"},
				"east": {"uv": [0, 0, 0, 6], "texture": "#1"},
				"south": {"uv": [5, 5, 10, 11], "texture": "#1"},
				"west": {"uv": [0, 0, 0, 6], "texture": "#1"},
				"up": {"uv": [0, 0, 5, 0], "texture": "#1"},
				"down": {"uv": [0, 0, 5, 0], "texture": "#1"}
			}
		},
		{
			"name": "bow top",
			"from": [-2.45, 10, 1.65],
			"to": [2.55, 16, 1.65],
			"rotation": {"angle": 0, "axis": "y", "origin": [13, 16, 2]},
			"faces": {
				"north": {"uv": [5, 5, 10, 11], "texture": "#1"},
				"east": {"uv": [0, 0, 0, 6], "texture": "#1"},
				"south": {"uv": [5, 5, 10, 11], "texture": "#1"},
				"west": {"uv": [0, 0, 0, 6], "texture": "#1"},
				"up": {"uv": [0, 0, 5, 0], "texture": "#1"},
				"down": {"uv": [0, 0, 5, 0], "texture": "#1"}
			}
		}
	],
	"display": {
		"thirdperson_righthand": {
			"rotation": [32, -90, 0],
			"translation": [-2.5, 0, -3],
			"scale": [0.5, 0.5, 0.5]
		},
		"thirdperson_lefthand": {
			"rotation": [24, 90, 0],
			"translation": [3.5, -0.25, -3.25],
			"scale": [0.5, 0.5, 0.5]
		},
		"gui": {
			"translation": [0, 1.75, 0],
			"scale": [0.7, 0.7, 0.7]
		},
		"fixed": {
			"rotation": [0, -180, 0],
			"translation": [0, 1, -5.25],
			"scale": [0.7, 0.7, 0.7]
		}
	},
	"groups": [
		0,
		1,
		2,
		3,
		4,
		5,
		6,
		7,
		{
			"name": "garland_horizontal",
			"origin": [8, 8, 8],
			"color": 0,
			"children": [8, 9, 10, 11, 12, 13, 14, 15]
		}
	]
}