{
	"credit": "Made with Blockbench",
	"parent": "block/block",
	"render_type": "cutout_mipped", "textures": {
		"0": "maidensmerrymaking:block/white_wire",
		"2": "maidensmerrymaking:block/twinkling_icicle_lights_multi_opposite",
		"3": "maidensmerrymaking:block/twinkling_icicle_lights_multi",
		"particle": "maidensmerrymaking:block/white_wire"
	},
	"elements": [
		{
			"name": "top_wire",
			"from": [8.7, 6, 15.95],
			"to": [11.1265, 7, 15.95],
			"rotation": {"angle": -45, "axis": "z", "origin": [8, 8, 8.8]},
			"faces": {
				"north": {"uv": [0, 0, 16, 1], "texture": "#0"},
				"east": {"uv": [0, 0, 1.2, 1], "texture": "#0"},
				"south": {"uv": [0, 0, 16, 1], "texture": "#0"},
				"west": {"uv": [0, 0, 1.2, 1], "texture": "#0"},
				"up": {"uv": [0, 0, 16, 1.2], "texture": "#0"},
				"down": {"uv": [0, 0, 16, 1.2], "texture": "#0"}
			}
		},
		{
			"name": "top_wire",
			"from": [6.4, 8, 15.95],
			"to": [7.4, 9, 15.95],
			"rotation": {"angle": -45, "axis": "z", "origin": [8, 8, 8.8]},
			"faces": {
				"north": {"uv": [0, 0, 16, 1], "texture": "#0"},
				"east": {"uv": [0, 0, 1.2, 1], "texture": "#0"},
				"south": {"uv": [0, 0, 16, 1], "texture": "#0"},
				"west": {"uv": [0, 0, 1.2, 1], "texture": "#0"},
				"up": {"uv": [0, 0, 16, 1.2], "texture": "#0"},
				"down": {"uv": [0, 0, 16, 1.2], "texture": "#0"}
			}
		},
		{
			"name": "top_wire",
			"from": [18.1, 8, 15.95],
			"to": [19.1, 9, 15.95],
			"rotation": {"angle": -45, "axis": "z", "origin": [8, 8, 8.8]},
			"faces": {
				"north": {"uv": [0, 0, 16, 1], "texture": "#0"},
				"east": {"uv": [0, 0, 1.2, 1], "texture": "#0"},
				"south": {"uv": [0, 0, 16, 1], "texture": "#0"},
				"west": {"uv": [0, 0, 1.2, 1], "texture": "#0"},
				"up": {"uv": [0, 0, 16, 1.2], "texture": "#0"},
				"down": {"uv": [0, 0, 16, 1.2], "texture": "#0"}
			}
		},
		{
			"name": "top_wire",
			"from": [2.7, 6, 15.95],
			"to": [5.1265, 7, 15.95],
			"rotation": {"angle": -45, "axis": "z", "origin": [8, 8, 8.8]},
			"faces": {
				"north": {"uv": [0, 0, 16, 1], "texture": "#0"},
				"east": {"uv": [0, 0, 1.2, 1], "texture": "#0"},
				"south": {"uv": [0, 0, 16, 1], "texture": "#0"},
				"west": {"uv": [0, 0, 1.2, 1], "texture": "#0"},
				"up": {"uv": [0, 0, 16, 1.2], "texture": "#0"},
				"down": {"uv": [0, 0, 16, 1.2], "texture": "#0"}
			}
		},
		{
			"name": "top_wire",
			"from": [5.2, 7, 15.95],
			"to": [6.4265, 8, 15.95],
			"rotation": {"angle": -45, "axis": "z", "origin": [8, 8, 8.8]},
			"faces": {
				"north": {"uv": [0, 0, 16, 1], "texture": "#0"},
				"east": {"uv": [0, 0, 1.2, 1], "texture": "#0"},
				"south": {"uv": [0, 0, 16, 1], "texture": "#0"},
				"west": {"uv": [0, 0, 1.2, 1], "texture": "#0"},
				"up": {"uv": [0, 0, 16, 1.2], "texture": "#0"},
				"down": {"uv": [0, 0, 16, 1.2], "texture": "#0"}
			}
		},
		{
			"name": "top_wire",
			"from": [7.45, 7, 15.95],
			"to": [8.6765, 8, 15.95],
			"rotation": {"angle": -45, "axis": "z", "origin": [8, 8, 8.8]},
			"faces": {
				"north": {"uv": [0, 0, 16, 1], "texture": "#0"},
				"east": {"uv": [0, 0, 1.2, 1], "texture": "#0"},
				"south": {"uv": [0, 0, 16, 1], "texture": "#0"},
				"west": {"uv": [0, 0, 1.2, 1], "texture": "#0"},
				"up": {"uv": [0, 0, 16, 1.2], "texture": "#0"},
				"down": {"uv": [0, 0, 16, 1.2], "texture": "#0"}
			}
		},
		{
			"name": "top_wire",
			"from": [11.1, 5, 15.95],
			"to": [14.6765, 6, 15.95],
			"rotation": {"angle": -45, "axis": "z", "origin": [8, 8, 8.8]},
			"faces": {
				"north": {"uv": [0, 0, 16, 1], "texture": "#0"},
				"east": {"uv": [0, 0, 1.2, 1], "texture": "#0"},
				"south": {"uv": [0, 0, 16, 1], "texture": "#0"},
				"west": {"uv": [0, 0, 1.2, 1], "texture": "#0"},
				"up": {"uv": [0, 0, 16, 1.2], "texture": "#0"},
				"down": {"uv": [0, 0, 16, 1.2], "texture": "#0"}
			}
		},
		{
			"name": "top_wire",
			"from": [-0.65, 5, 15.95],
			"to": [2.6765, 6, 15.95],
			"rotation": {"angle": -45, "axis": "z", "origin": [8, 8, 8.8]},
			"faces": {
				"north": {"uv": [0, 0, 16, 1], "texture": "#0"},
				"east": {"uv": [0, 0, 1.2, 1], "texture": "#0"},
				"south": {"uv": [0, 0, 16, 1], "texture": "#0"},
				"west": {"uv": [0, 0, 1.2, 1], "texture": "#0"},
				"up": {"uv": [0, 0, 16, 1.2], "texture": "#0"},
				"down": {"uv": [0, 0, 16, 1.2], "texture": "#0"}
			}
		},
		{
			"name": "top_wire",
			"from": [14.7, 6, 15.95],
			"to": [17.1265, 7, 15.95],
			"rotation": {"angle": -45, "axis": "z", "origin": [8, 8, 8.8]},
			"faces": {
				"north": {"uv": [0, 0, 16, 1], "texture": "#0"},
				"east": {"uv": [0, 0, 1.2, 1], "texture": "#0"},
				"south": {"uv": [0, 0, 16, 1], "texture": "#0"},
				"west": {"uv": [0, 0, 1.2, 1], "texture": "#0"},
				"up": {"uv": [0, 0, 16, 1.2], "texture": "#0"},
				"down": {"uv": [0, 0, 16, 1.2], "texture": "#0"}
			}
		},
		{
			"name": "top_wire",
			"from": [20, 6, 15.95],
			"to": [21.8265, 7, 15.95],
			"rotation": {"angle": -45, "axis": "z", "origin": [8, 8, 8.8]},
			"faces": {
				"north": {"uv": [0, 0, 16, 1], "texture": "#0"},
				"east": {"uv": [0, 0, 1.2, 1], "texture": "#0"},
				"south": {"uv": [0, 0, 16, 1], "texture": "#0"},
				"west": {"uv": [0, 0, 1.2, 1], "texture": "#0"},
				"up": {"uv": [0, 0, 16, 1.2], "texture": "#0"},
				"down": {"uv": [0, 0, 16, 1.2], "texture": "#0"}
			}
		},
		{
			"name": "top_wire",
			"from": [17.15, 7, 15.95],
			"to": [18.15, 8, 15.95],
			"rotation": {"angle": -45, "axis": "z", "origin": [8, 8, 8.8]},
			"faces": {
				"north": {"uv": [0, 0, 16, 1], "texture": "#0"},
				"east": {"uv": [0, 0, 1.2, 1], "texture": "#0"},
				"south": {"uv": [0, 0, 16, 1], "texture": "#0"},
				"west": {"uv": [0, 0, 1.2, 1], "texture": "#0"},
				"up": {"uv": [0, 0, 16, 1.2], "texture": "#0"},
				"down": {"uv": [0, 0, 16, 1.2], "texture": "#0"}
			}
		},
		{
			"name": "top_wire",
			"from": [19.05, 7, 15.95],
			"to": [20.05, 8, 15.95],
			"rotation": {"angle": -45, "axis": "z", "origin": [8, 8, 8.8]},
			"faces": {
				"north": {"uv": [0, 0, 16, 1], "texture": "#0"},
				"east": {"uv": [0, 0, 1.2, 1], "texture": "#0"},
				"south": {"uv": [0, 0, 16, 1], "texture": "#0"},
				"west": {"uv": [0, 0, 1.2, 1], "texture": "#0"},
				"up": {"uv": [0, 0, 16, 1.2], "texture": "#0"},
				"down": {"uv": [0, 0, 16, 1.2], "texture": "#0"}
			}
		},
		{
			"from": [6.25, -7.5, 15.85],
			"to": [7.25, 9.1, 15.85],
			"rotation": {"angle": 0, "axis": "y", "origin": [8.25, -5, 8.8]},
			"faces": {
				"north": {"uv": [0, 0, 1, 1], "texture": "#0"},
				"east": {"uv": [0, 0, 1, 1], "texture": "#0"},
				"south": {"uv": [0, 0, 1, 1], "texture": "#0"},
				"west": {"uv": [0, 0, 1, 1], "texture": "#0"},
				"up": {"uv": [0, 0, 1, 1], "texture": "#0"},
				"down": {"uv": [0, 0, 1, 1], "texture": "#0"}
			}
		},
		{
			"from": [1, -3, 15.85],
			"to": [2, 10.75, 15.85],
			"rotation": {"angle": 0, "axis": "y", "origin": [7, 2.75, -5.2]},
			"faces": {
				"north": {"uv": [0, 0, 1, 15], "texture": "#0"},
				"east": {"uv": [0, 0, 1, 15], "texture": "#0"},
				"south": {"uv": [0, 0, 1, 15], "texture": "#0"},
				"west": {"uv": [0, 0, 1, 15], "texture": "#0"},
				"up": {"uv": [0, 0, 1, 1], "texture": "#0"},
				"down": {"uv": [0, 0, 1, 1], "texture": "#0"}
			}
		},
		{
			"from": [11.75, -13, 15.85],
			"to": [12.75, 1.75, 15.85],
			"rotation": {"angle": 0, "axis": "y", "origin": [9.75, -6.25, -5.2]},
			"faces": {
				"north": {"uv": [0, 0, 1, 15], "texture": "#0"},
				"east": {"uv": [0, 0, 1, 15], "texture": "#0"},
				"south": {"uv": [0, 0, 1, 15], "texture": "#0"},
				"west": {"uv": [0, 0, 1, 15], "texture": "#0"},
				"up": {"uv": [0, 0, 1, 1], "texture": "#0"},
				"down": {"uv": [0, 0, 1, 1], "texture": "#0"}
			}
		},
		{
			"name": "south",
			"from": [1, -4, 15.7],
			"to": [5, 0, 15.7],
			"shade": false,
			"rotation": {"angle": 0, "axis": "y", "origin": [0, 0, 0.8]},
			"faces": {
				"north": {"uv": [10, 5, 14, 9], "texture": "#2"},
				"east": {"uv": [10, 5, 14, 9], "texture": "#2"},
				"south": {"uv": [10, 5, 14, 9], "texture": "#2"},
				"west": {"uv": [10, 5, 14, 9], "texture": "#2"},
				"up": {"uv": [0, 0, 4, 0], "texture": "#2"},
				"down": {"uv": [0, 0, 4, 0], "texture": "#2"}
			}
		},
		{
			"name": "south",
			"from": [8.75, -14, 15.7],
			"to": [12.75, -10, 15.7],
			"shade": false,
			"rotation": {"angle": 0, "axis": "y", "origin": [0, 0, 0.8]},
			"faces": {
				"north": {"uv": [0, 5, 4, 9], "texture": "#2"},
				"east": {"uv": [0, 5, 4, 9], "texture": "#2"},
				"south": {"uv": [0, 5, 4, 9], "texture": "#2"},
				"west": {"uv": [0, 5, 4, 9], "texture": "#2"},
				"up": {"uv": [0, 0, 4, 0], "texture": "#2"},
				"down": {"uv": [0, 0, 4, 0], "texture": "#2"}
			}
		},
		{
			"name": "south",
			"from": [3.25, -8.5, 15.7],
			"to": [7.25, -4.5, 15.7],
			"shade": false,
			"rotation": {"angle": 0, "axis": "y", "origin": [0, 0, 0.8]},
			"faces": {
				"north": {"uv": [0, 10, 4, 14], "texture": "#3"},
				"east": {"uv": [0, 10, 4, 14], "texture": "#3"},
				"south": {"uv": [0, 10, 4, 14], "texture": "#3"},
				"west": {"uv": [0, 10, 4, 14], "texture": "#3"},
				"up": {"uv": [0, 0, 4, 0], "texture": "#3"},
				"down": {"uv": [0, 0, 4, 0], "texture": "#3"}
			}
		},
		{
			"name": "south",
			"from": [-2, 0.5, 15.7],
			"to": [2, 4.5, 15.7],
			"shade": false,
			"rotation": {"angle": 0, "axis": "y", "origin": [0, 0, 0.8]},
			"faces": {
				"north": {"uv": [10, 0, 14, 4], "texture": "#3"},
				"east": {"uv": [10, 0, 14, 4], "texture": "#3"},
				"south": {"uv": [10, 0, 14, 4], "texture": "#3"},
				"west": {"uv": [10, 0, 14, 4], "texture": "#3"},
				"up": {"uv": [0, 0, 4, 0], "texture": "#3"},
				"down": {"uv": [0, 0, 4, 0], "texture": "#3"}
			}
		},
		{
			"name": "south",
			"from": [8.75, -4, 15.7],
			"to": [12.75, 0, 15.7],
			"shade": false,
			"rotation": {"angle": 0, "axis": "y", "origin": [0, 0, 0.8]},
			"faces": {
				"north": {"uv": [5, 5, 9, 9], "texture": "#2"},
				"east": {"uv": [5, 5, 9, 9], "texture": "#2"},
				"south": {"uv": [5, 5, 9, 9], "texture": "#2"},
				"west": {"uv": [5, 5, 9, 9], "texture": "#2"},
				"up": {"uv": [0, 0, 4, 0], "texture": "#2"},
				"down": {"uv": [0, 0, 4, 0], "texture": "#2"}
			}
		},
		{
			"name": "south",
			"from": [11.75, -8.5, 15.7],
			"to": [15.75, -4.5, 15.7],
			"shade": false,
			"rotation": {"angle": 0, "axis": "y", "origin": [0, 0, 0.8]},
			"faces": {
				"north": {"uv": [5, 0, 9, 4], "texture": "#3"},
				"east": {"uv": [5, 0, 9, 4], "texture": "#3"},
				"south": {"uv": [5, 0, 9, 4], "texture": "#3"},
				"west": {"uv": [5, 0, 9, 4], "texture": "#3"},
				"up": {"uv": [0, 0, 4, 0], "texture": "#3"},
				"down": {"uv": [0, 0, 4, 0], "texture": "#3"}
			}
		},
		{
			"name": "south",
			"from": [3.25, 3.5, 15.7],
			"to": [7.25, 7.5, 15.7],
			"shade": false,
			"rotation": {"angle": 0, "axis": "y", "origin": [0, 0, 0.8]},
			"faces": {
				"north": {"uv": [0, 0, 4, 4], "texture": "#2"},
				"east": {"uv": [0, 0, 4, 4], "texture": "#2"},
				"south": {"uv": [0, 0, 4, 4], "texture": "#2"},
				"west": {"uv": [0, 0, 4, 4], "texture": "#2"},
				"up": {"uv": [0, 0, 4, 0], "texture": "#2"},
				"down": {"uv": [0, 0, 4, 0], "texture": "#2"}
			}
		}
	],
	"display": {
		"thirdperson_righthand": {
			"rotation": [17, -75, -63],
			"translation": [4, -1.25, 0],
			"scale": [0.5, 0.5, 0.5]
		}
	},
	"groups": [
		{
			"name": "diagonal_left_icicle_testing_swoop",
			"origin": [8, 8, 8],
			"color": 0,
			"shade": false,
			"children": [
				{
					"name": "wires",
					"origin": [8, 8, 8],
					"color": 0,
					"children": [
						{
							"name": "swooping_wires",
							"origin": [8, 8, 8],
							"color": 0,
							"children": [0, 1, 2, 3, 4, 5, 6, 7, 8, 9, 10, 11]
						}
					]
				},
				{
					"name": "horizontal_icicle_lights_white",
					"origin": [8, 8, 8],
					"color": 0,
					"children": [
						{
							"name": "vertical_wires",
							"origin": [8, 8, 8],
							"color": 0,
							"children": []
						},
						12,
						13,
						14
					]
				},
				{
					"name": "bulbs",
					"origin": [8, 8, 8],
					"color": 0,
					"shade": false,
					"children": [
						{
							"name": "test style",
							"origin": [8, 8, 8],
							"color": 0,
							"shade": false,
							"children": [15]
						},
						{
							"name": "test style",
							"origin": [8, 8, 8],
							"color": 0,
							"shade": false,
							"children": [16]
						},
						{
							"name": "test style",
							"origin": [8, 8, 8],
							"color": 0,
							"shade": false,
							"children": [17]
						},
						{
							"name": "test style",
							"origin": [8, 8, 8],
							"color": 0,
							"shade": false,
							"children": [18]
						},
						{
							"name": "test style",
							"origin": [8, 8, 8],
							"color": 0,
							"shade": false,
							"children": [19]
						},
						{
							"name": "test style",
							"origin": [8, 8, 8],
							"color": 0,
							"shade": false,
							"children": [20]
						},
						{
							"name": "test style",
							"origin": [8, 8, 8],
							"color": 0,
							"shade": false,
							"children": [21]
						}
					]
				}
			]
		}
	]
}